bot/__init__.py
bot/__main__.py
bot/modules/__init__.py
bot/modules/anilist.py
bot/modules/authorize.py
bot/modules/bot_settings.py
bot/modules/broadcast.py
bot/modules/bt_select.py
bot/modules/cancel_mirror.py
bot/modules/clone.py
bot/modules/count.py
bot/modules/delete.py
bot/modules/drive_clean.py
bot/modules/eval.py
bot/modules/gmail.py
bot/modules/hash.py
bot/modules/imdb.py
bot/modules/list.py
bot/modules/listener.py
bot/modules/mediainfo.py
bot/modules/mirror_leech.py
bot/modules/mirror_status.py
bot/modules/pictures.py
bot/modules/rss.py
bot/modules/save_msg.py
bot/modules/scraper.py
bot/modules/search.py
bot/modules/sel_cat.py
bot/modules/shell.py
bot/modules/speedtest.py
bot/modules/users.py
bot/modules/users_settings.py
bot/modules/wayback.py
bot/modules/ytdlp.py
web/__init__.py
web/nodes.py
web/wserver.py
mirrorbot-0.3.dist-info/LICENSE
mirrorbot-0.3.dist-info/METADATA
mirrorbot-0.3.dist-info/WHEEL
mirrorbot-0.3.dist-info/entry_points.txt
mirrorbot-0.3.dist-info/top_level.txt
mirrorbot-0.3.dist-info/RECORD
